jike/__init__.py
jike/client.py
jike/constants.py
jike/qr_code.py
jike/session.py
jike/utils.py
jike/objects/__init__.py
jike/objects/base.py
jike/objects/message.py
jike/objects/topic.py
jike/objects/user.py
jike/objects/wrapper.py
jike-0.4.0.dist-info/DESCRIPTION.rst
jike-0.4.0.dist-info/LICENSE.txt
jike-0.4.0.dist-info/METADATA
jike-0.4.0.dist-info/RECORD
jike-0.4.0.dist-info/WHEEL
jike-0.4.0.dist-info/metadata.json
jike-0.4.0.dist-info/top_level.txt
