Metadata-Version: 2.0
Name: jike
Version: 0.4.0
Summary: Ⓙ Jike Metro: Unofficial Jike Client
Home-page: https://github.com/Sorosliu1029/Jike-Metro
Author: Soros Liu
Author-email: soros.liu1029@gmail.com
License: MIT
Project-URL: Bug Reports, https://github.com/Sorosliu1029/Jike-Metro/issues
Project-URL: Say Thanks!, http://saythanks.io/to/Sorosliu1029
Project-URL: Source, https://github.com/Sorosliu1029/Jike-Metro/
Keywords: jike crawl
Platform: UNKNOWN
Classifier: Development Status :: 4 - Beta
Classifier: Intended Audience :: Developers
Classifier: Topic :: Software Development :: Build Tools
Classifier: Topic :: Internet :: WWW/HTTP :: Browsers
Classifier: License :: OSI Approved :: MIT License
Classifier: Programming Language :: Python :: 3
Classifier: Programming Language :: Python :: 3.4
Classifier: Programming Language :: Python :: 3.5
Classifier: Programming Language :: Python :: 3.6
Classifier: Programming Language :: Python :: Implementation :: CPython
Classifier: Programming Language :: Python :: Implementation :: PyPy
Requires-Python: !=3.0.*, !=3.1.*, !=3.2.*, !=3.3.*
Requires-Dist: requests (>=2.18.0)
Requires-Dist: pillow (>=3.4.0)
Requires-Dist: qrcode (>=5.3)
Provides-Extra: doc
Requires-Dist: nbconvert (>=5.3.0); extra == 'doc'
Provides-Extra: test
Requires-Dist: responses (>=0.8.0); extra == 'test'
